mesh_to_sim_asset/__init__.py
mesh_to_sim_asset/canonicalize.py
mesh_to_sim_asset/create_drake_assets_from_geometry.py
mesh_to_sim_asset/dynamic_eval.py
mesh_to_sim_asset/make_asset_drake_compatible.py
mesh_to_sim_asset/mesh_conversion.py
mesh_to_sim_asset/mesh_simplification.py
mesh_to_sim_asset/mesh_to_vtk.py
mesh_to_sim_asset/objaverse.py
mesh_to_sim_asset/physics.py
mesh_to_sim_asset/pose_utils.py
mesh_to_sim_asset/sdformat.py
mesh_to_sim_asset/sim_metrics.py
mesh_to_sim_asset/usd_to_sdf.py
mesh_to_sim_asset/util.py
mesh_to_sim_asset/data/__init__.py
mesh_to_sim_asset/data/composed_physics_system_prompt.txt
mesh_to_sim_asset/data/materials.yaml
mesh_to_sim_asset/data/physics_system_prompt.txt
mesh_to_sim_asset/data/studio.blend
create_drake_asset_from_geometry.py
make_asset_drake_compatible.py
mesh_to_sim_asset-0.1.5.dist-info/METADATA
mesh_to_sim_asset-0.1.5.dist-info/WHEEL
mesh_to_sim_asset-0.1.5.dist-info/RECORD
