Metadata-Version: 2.4
Name: mesh-to-sim-asset
Version: 0.1.5
Summary: Pipeline for converting mesh files into simulation assets
Requires-Python: <3.11,>=3.10
Requires-Dist: black==25.1.0
Requires-Dist: bpy==4.0.0
Requires-Dist: coacd>=1.0.7
Requires-Dist: datasets>=4.0.0
Requires-Dist: drake>=1.43.0
Requires-Dist: ipython>=8.37.0
Requires-Dist: isort==5.12.0
Requires-Dist: lxml>=5.4.0
Requires-Dist: manipulation>=2025.5.18
Requires-Dist: numpy>=2.2.6
Requires-Dist: objaverse>=0.1.7
Requires-Dist: openai>=1.12.0
Requires-Dist: pandas>=2.3.1
Requires-Dist: pillow>=10.2.0
Requires-Dist: pycollada>=0.9.2
Requires-Dist: pyvista>=0.45.2
Requires-Dist: scipy>=1.15.3
Requires-Dist: tetgen>=0.6.5
Requires-Dist: tqdm>=4.67.1
Requires-Dist: trimesh>=4.6.10
Requires-Dist: vhacdx>=0.0.8.post2
